config/__init__.py
config/config_apis.py
config/config_aws.py
bayoukanji-0.1.dist-info/METADATA
bayoukanji-0.1.dist-info/WHEEL
bayoukanji-0.1.dist-info/top_level.txt
bayoukanji-0.1.dist-info/RECORD
