Metadata-Version: 2.1
Name: bayoukanji
Version: 0.1
Summary: Pacote config para projeto Bayou
Home-page: https://github.com/DouglasBMart/bayoukanji.git
Author: Douglas
Author-email: douglas@meizter.com
Classifier: Programming Language :: Python :: 3
Classifier: License :: OSI Approved :: MIT License
Classifier: Operating System :: OS Independent
Requires-Python: >=3.6
Requires-Dist: requests
Requires-Dist: pandas
Requires-Dist: s3fs
Requires-Dist: boto3
Requires-Dist: pyarrow
